skills_mcp/__init__.py
skills_mcp/api.py
skills_mcp/config.py
skills_mcp/local.py
skills_mcp/server.py
skills_mcp/utils.py
skills_mcp-0.1.2.dist-info/METADATA
skills_mcp-0.1.2.dist-info/WHEEL
skills_mcp-0.1.2.dist-info/entry_points.txt
skills_mcp-0.1.2.dist-info/RECORD
