Metadata-Version: 2.4
Name: skills-mcp
Version: 0.1.2
Summary: A Model Context Protocol (MCP) server for managing AI Agent Skills.
Project-URL: Homepage, https://github.com/leezhuuuuu/skills-mcp
Project-URL: Repository, https://github.com/leezhuuuuu/skills-mcp
Project-URL: Documentation, https://skills.leezhu.cn
Author-email: Leezhu <me@leezhu.cn>
License: MIT
Keywords: agent,ai,claude,mcp,skills
Classifier: Development Status :: 4 - Beta
Classifier: Intended Audience :: Developers
Classifier: Programming Language :: Python :: 3
Classifier: Programming Language :: Python :: 3.10
Classifier: Programming Language :: Python :: 3.11
Classifier: Programming Language :: Python :: 3.12
Classifier: Topic :: Software Development :: Libraries :: Application Frameworks
Requires-Python: >=3.10
Requires-Dist: httpx>=0.27.0
Requires-Dist: mcp[fastmcp]>=1.0.0
